{
  "sum(irate(container_cpu_user_seconds_total{name=\"srsdu5\",instance=\"cadvisor:8080\"}[5m]) * 100)by (instance) / sum(machine_cpu_cores{instance=\"cadvisor:8080\"}) by (instance)": 3.7025687172774613,
  "((sum(container_memory_usage_bytes{name=\"srsdu5\",instance=\"cadvisor:8080\"}) by (instance) - sum(container_memory_cache{name=\"srsdu5\",instance=\"cadvisor:8080\"}) by (instance)) / sum(machine_memory_bytes{instance=\"cadvisor:8080\"}) by (instance)) * 100": 3.718419023583515,
  "sum(container_memory_usage_bytes{name=\"srsdu5\",instance=\"cadvisor:8080\"}) by (instance) - sum(container_memory_cache{name=\"srsdu5\",instance=\"cadvisor:8080\"}) by (instance)": 2494857216.0,
  "sum(irate(container_network_transmit_bytes_total{name=\"srsdu5\",instance=\"cadvisor:8080\",interface=\"eth0\"}[5m]))by (instance)": 161829948.95287958,
  "sum(irate(container_network_transmit_bytes_total{name=\"srsdu5\",instance=\"cadvisor:8080\",interface=\"eth1\"}[5m]))by (instance)": 11633.507853403142,
  "sum(irate(container_network_receive_bytes_total{name=\"srsdu5\",instance=\"cadvisor:8080\",interface=\"eth0\"}[5m]))by (instance)": 161640801.04712042,
  "sum(irate(container_network_receive_bytes_total{name=\"srsdu5\",instance=\"cadvisor:8080\",interface=\"eth1\"}[5m]))by (instance)": 0.0,
  "sum  (irate(container_cpu_user_seconds_total{name=\"srsdu5\",instance=\"cadvisor:8080\"}[5m]) * 100)": 103.67192408376891,
  "sum  (container_memory_usage_bytes{name=\"srsdu5\",instance=\"cadvisor:8080\"} - container_memory_cache{name=\"srsdu5\",instance=\"cadvisor:8080\"})": 2494857216.0,
  "sum  (irate(container_network_transmit_bytes_total{name=\"srsdu5\",instance=\"cadvisor:8080\",interface=\"eth0\"}[5m]))": 161829948.95287958,
  "sum  (irate(container_network_transmit_bytes_total{name=\"srsdu5\",instance=\"cadvisor:8080\",interface=\"eth1\"}[5m]))": 11633.507853403142,
  "sum  (irate(container_network_receive_bytes_total{name=\"srsdu5\",instance=\"cadvisor:8080\",interface=\"eth0\"}[5m]))": 161640801.04712042,
  "sum  (irate(container_network_receive_bytes_total{name=\"srsdu5\",instance=\"cadvisor:8080\",interface=\"eth1\"}[5m]))": 0.0,
  "sum(irate(container_cpu_user_seconds_total{name=\"srscu0\",instance=\"cadvisor:8080\"}[5m]) * 100)by (instance) / sum(machine_cpu_cores{instance=\"cadvisor:8080\"}) by (instance)": 0.22229155602761486,
  "((sum(container_memory_usage_bytes{name=\"srscu0\",instance=\"cadvisor:8080\"}) by (instance) - sum(container_memory_cache{name=\"srscu0\",instance=\"cadvisor:8080\"}) by (instance)) / sum(machine_memory_bytes{instance=\"cadvisor:8080\"}) by (instance)) * 100": 3.3963228251135034,
  "sum(container_memory_usage_bytes{name=\"srscu0\",instance=\"cadvisor:8080\"}) by (instance) - sum(container_memory_cache{name=\"srscu0\",instance=\"cadvisor:8080\"}) by (instance)": 2278748160.0,
  "sum(irate(container_network_transmit_bytes_total{name=\"srscu0\",instance=\"cadvisor:8080\",interface=\"eth0\"}[5m]))by (instance)": 577351.9206939281,
  "sum(irate(container_network_transmit_bytes_total{name=\"srscu0\",instance=\"cadvisor:8080\",interface=\"eth1\"}[5m]))by (instance)": 1418.8351920693926,
  "sum(irate(container_network_receive_bytes_total{name=\"srscu0\",instance=\"cadvisor:8080\",interface=\"eth0\"}[5m]))by (instance)": 575579.9256505576,
  "sum(irate(container_network_receive_bytes_total{name=\"srscu0\",instance=\"cadvisor:8080\",interface=\"eth1\"}[5m]))by (instance)": 43.37050805452292,
  "sum  (irate(container_cpu_user_seconds_total{name=\"srscu0\",instance=\"cadvisor:8080\"}[5m]) * 100)": 6.224163568773216,
  "sum  (container_memory_usage_bytes{name=\"srscu0\",instance=\"cadvisor:8080\"} - container_memory_cache{name=\"srscu0\",instance=\"cadvisor:8080\"})": 2278748160.0,
  "sum  (irate(container_network_transmit_bytes_total{name=\"srscu0\",instance=\"cadvisor:8080\",interface=\"eth0\"}[5m]))": 577351.9206939281,
  "sum  (irate(container_network_transmit_bytes_total{name=\"srscu0\",instance=\"cadvisor:8080\",interface=\"eth1\"}[5m]))": 1418.8351920693926,
  "sum  (irate(container_network_receive_bytes_total{name=\"srscu0\",instance=\"cadvisor:8080\",interface=\"eth0\"}[5m]))": 575579.9256505576,
  "sum  (irate(container_network_receive_bytes_total{name=\"srscu0\",instance=\"cadvisor:8080\",interface=\"eth1\"}[5m]))": 43.37050805452292,
  "sum(irate(container_cpu_user_seconds_total{name=\"srsdu0\",instance=\"cadvisor:8080\"}[5m]) * 100)by (instance) / sum(machine_cpu_cores{instance=\"cadvisor:8080\"}) by (instance)": 3.6954733842766623,
  "((sum(container_memory_usage_bytes{name=\"srsdu0\",instance=\"cadvisor:8080\"}) by (instance) - sum(container_memory_cache{name=\"srsdu0\",instance=\"cadvisor:8080\"}) by (instance)) / sum(machine_memory_bytes{instance=\"cadvisor:8080\"}) by (instance)) * 100": 3.7187425788330155,
  "sum(container_memory_usage_bytes{name=\"srsdu0\",instance=\"cadvisor:8080\"}) by (instance) - sum(container_memory_cache{name=\"srsdu0\",instance=\"cadvisor:8080\"}) by (instance)": 2495074304.0,
  "sum(irate(container_network_transmit_bytes_total{name=\"srsdu0\",instance=\"cadvisor:8080\",interface=\"eth0\"}[5m]))by (instance)": 162295330.0090662,
  "sum(irate(container_network_transmit_bytes_total{name=\"srsdu0\",instance=\"cadvisor:8080\",interface=\"eth1\"}[5m]))by (instance)": 15884.859474161378,
  "sum(irate(container_network_receive_bytes_total{name=\"srsdu0\",instance=\"cadvisor:8080\",interface=\"eth0\"}[5m]))by (instance)": 162385202.17588395,
  "sum(irate(container_network_receive_bytes_total{name=\"srsdu0\",instance=\"cadvisor:8080\",interface=\"eth1\"}[5m]))by (instance)": 0.0,
  "sum  (irate(container_cpu_user_seconds_total{name=\"srsdu0\",instance=\"cadvisor:8080\"}[5m]) * 100)": 103.47325475974654,
  "sum  (container_memory_usage_bytes{name=\"srsdu0\",instance=\"cadvisor:8080\"} - container_memory_cache{name=\"srsdu0\",instance=\"cadvisor:8080\"})": 2495074304.0,
  "sum  (irate(container_network_transmit_bytes_total{name=\"srsdu0\",instance=\"cadvisor:8080\",interface=\"eth0\"}[5m]))": 162295330.0090662,
  "sum  (irate(container_network_transmit_bytes_total{name=\"srsdu0\",instance=\"cadvisor:8080\",interface=\"eth1\"}[5m]))": 15884.859474161378,
  "sum  (irate(container_network_receive_bytes_total{name=\"srsdu0\",instance=\"cadvisor:8080\",interface=\"eth0\"}[5m]))": 162385202.17588395,
  "sum  (irate(container_network_receive_bytes_total{name=\"srsdu0\",instance=\"cadvisor:8080\",interface=\"eth1\"}[5m]))": 0.0,
  "sum(irate(container_cpu_user_seconds_total{name=\"srsdu3\",instance=\"cadvisor:8080\"}[5m]) * 100)by (instance) / sum(machine_cpu_cores{instance=\"cadvisor:8080\"}) by (instance)": 3.753233305156375,
  "((sum(container_memory_usage_bytes{name=\"srsdu3\",instance=\"cadvisor:8080\"}) by (instance) - sum(container_memory_cache{name=\"srsdu3\",instance=\"cadvisor:8080\"}) by (instance)) / sum(machine_memory_bytes{instance=\"cadvisor:8080\"}) by (instance)) * 100": 3.7191210774267716,
  "sum(container_memory_usage_bytes{name=\"srsdu3\",instance=\"cadvisor:8080\"}) by (instance) - sum(container_memory_cache{name=\"srsdu3\",instance=\"cadvisor:8080\"}) by (instance)": 2495328256.0,
  "sum(irate(container_network_transmit_bytes_total{name=\"srsdu3\",instance=\"cadvisor:8080\",interface=\"eth0\"}[5m]))by (instance)": 166360722.96933836,
  "sum(irate(container_network_transmit_bytes_total{name=\"srsdu3\",instance=\"cadvisor:8080\",interface=\"eth1\"}[5m]))by (instance)": 15538.999462076385,
  "sum(irate(container_network_receive_bytes_total{name=\"srsdu3\",instance=\"cadvisor:8080\",interface=\"eth0\"}[5m]))by (instance)": 166111135.55675095,
  "sum(irate(container_network_receive_bytes_total{name=\"srsdu3\",instance=\"cadvisor:8080\",interface=\"eth1\"}[5m]))by (instance)": 0.0,
  "sum  (irate(container_cpu_user_seconds_total{name=\"srsdu3\",instance=\"cadvisor:8080\"}[5m]) * 100)": 105.0905325443785,
  "sum  (container_memory_usage_bytes{name=\"srsdu3\",instance=\"cadvisor:8080\"} - container_memory_cache{name=\"srsdu3\",instance=\"cadvisor:8080\"})": 2495328256.0,
  "sum  (irate(container_network_transmit_bytes_total{name=\"srsdu3\",instance=\"cadvisor:8080\",interface=\"eth0\"}[5m]))": 166360722.96933836,
  "sum  (irate(container_network_transmit_bytes_total{name=\"srsdu3\",instance=\"cadvisor:8080\",interface=\"eth1\"}[5m]))": 15538.999462076385,
  "sum  (irate(container_network_receive_bytes_total{name=\"srsdu3\",instance=\"cadvisor:8080\",interface=\"eth0\"}[5m]))": 166111135.55675095,
  "sum  (irate(container_network_receive_bytes_total{name=\"srsdu3\",instance=\"cadvisor:8080\",interface=\"eth1\"}[5m]))": 0.0,
  "sum(irate(container_cpu_user_seconds_total{name=\"hbbr\",instance=\"cadvisor:8080\"}[5m]) * 100)by (instance) / sum(machine_cpu_cores{instance=\"cadvisor:8080\"}) by (instance)": 0.0,
  "((sum(container_memory_usage_bytes{name=\"hbbr\",instance=\"cadvisor:8080\"}) by (instance) - sum(container_memory_cache{name=\"hbbr\",instance=\"cadvisor:8080\"}) by (instance)) / sum(machine_memory_bytes{instance=\"cadvisor:8080\"}) by (instance)) * 100": 0.0,
  "sum(container_memory_usage_bytes{name=\"hbbr\",instance=\"cadvisor:8080\"}) by (instance) - sum(container_memory_cache{name=\"hbbr\",instance=\"cadvisor:8080\"}) by (instance)": 0.0,
  "sum(irate(container_network_transmit_bytes_total{name=\"hbbr\",instance=\"cadvisor:8080\",interface=\"eth0\"}[5m]))by (instance)": 0.0,
  "sum(irate(container_network_transmit_bytes_total{name=\"hbbr\",instance=\"cadvisor:8080\",interface=\"eth1\"}[5m]))by (instance)": 0.0,
  "sum(irate(container_network_receive_bytes_total{name=\"hbbr\",instance=\"cadvisor:8080\",interface=\"eth0\"}[5m]))by (instance)": 0.0,
  "sum(irate(container_network_receive_bytes_total{name=\"hbbr\",instance=\"cadvisor:8080\",interface=\"eth1\"}[5m]))by (instance)": 0.0,
  "sum  (irate(container_cpu_user_seconds_total{name=\"hbbr\",instance=\"cadvisor:8080\"}[5m]) * 100)": 0.0,
  "sum  (container_memory_usage_bytes{name=\"hbbr\",instance=\"cadvisor:8080\"} - container_memory_cache{name=\"hbbr\",instance=\"cadvisor:8080\"})": 0.0,
  "sum  (irate(container_network_transmit_bytes_total{name=\"hbbr\",instance=\"cadvisor:8080\",interface=\"eth0\"}[5m]))": 0.0,
  "sum  (irate(container_network_transmit_bytes_total{name=\"hbbr\",instance=\"cadvisor:8080\",interface=\"eth1\"}[5m]))": 0.0,
  "sum  (irate(container_network_receive_bytes_total{name=\"hbbr\",instance=\"cadvisor:8080\",interface=\"eth0\"}[5m]))": 0.0,
  "sum  (irate(container_network_receive_bytes_total{name=\"hbbr\",instance=\"cadvisor:8080\",interface=\"eth1\"}[5m]))": 0.0,
  "sum(irate(container_cpu_user_seconds_total{name=\"srsdu4\",instance=\"cadvisor:8080\"}[5m]) * 100)by (instance) / sum(machine_cpu_cores{instance=\"cadvisor:8080\"}) by (instance)": 3.686331947162348,
  "((sum(container_memory_usage_bytes{name=\"srsdu4\",instance=\"cadvisor:8080\"}) by (instance) - sum(container_memory_cache{name=\"srsdu4\",instance=\"cadvisor:8080\"}) by (instance)) / sum(machine_memory_bytes{instance=\"cadvisor:8080\"}) by (instance)) * 100": 3.718779207729186,
  "sum(container_memory_usage_bytes{name=\"srsdu4\",instance=\"cadvisor:8080\"}) by (instance) - sum(container_memory_cache{name=\"srsdu4\",instance=\"cadvisor:8080\"}) by (instance)": 2495098880.0,
  "sum(irate(container_network_transmit_bytes_total{name=\"srsdu4\",instance=\"cadvisor:8080\",interface=\"eth0\"}[5m]))by (instance)": 159450492.29452056,
  "sum(irate(container_network_transmit_bytes_total{name=\"srsdu4\",instance=\"cadvisor:8080\",interface=\"eth1\"}[5m]))by (instance)": 15224.315068493152,
  "sum(irate(container_network_receive_bytes_total{name=\"srsdu4\",instance=\"cadvisor:8080\",interface=\"eth0\"}[5m]))by (instance)": 159173380.99315068,
  "sum(irate(container_network_receive_bytes_total{name=\"srsdu4\",instance=\"cadvisor:8080\",interface=\"eth1\"}[5m]))by (instance)": 35.95890410958904,
  "sum  (irate(container_cpu_user_seconds_total{name=\"srsdu4\",instance=\"cadvisor:8080\"}[5m]) * 100)": 103.21729452054575,
  "sum  (container_memory_usage_bytes{name=\"srsdu4\",instance=\"cadvisor:8080\"} - container_memory_cache{name=\"srsdu4\",instance=\"cadvisor:8080\"})": 2495098880.0,
  "sum  (irate(container_network_transmit_bytes_total{name=\"srsdu4\",instance=\"cadvisor:8080\",interface=\"eth0\"}[5m]))": 159450492.29452056,
  "sum  (irate(container_network_transmit_bytes_total{name=\"srsdu4\",instance=\"cadvisor:8080\",interface=\"eth1\"}[5m]))": 15224.315068493152,
  "sum  (irate(container_network_receive_bytes_total{name=\"srsdu4\",instance=\"cadvisor:8080\",interface=\"eth0\"}[5m]))": 159173380.99315068,
  "sum  (irate(container_network_receive_bytes_total{name=\"srsdu4\",instance=\"cadvisor:8080\",interface=\"eth1\"}[5m]))": 35.95890410958904,
  "sum(irate(container_cpu_user_seconds_total{name=\"open5gs_5gc\",instance=\"cadvisor:8080\"}[5m]) * 100)by (instance) / sum(machine_cpu_cores{instance=\"cadvisor:8080\"}) by (instance)": 0.08936455847255156,
  "((sum(container_memory_usage_bytes{name=\"open5gs_5gc\",instance=\"cadvisor:8080\"}) by (instance) - sum(container_memory_cache{name=\"open5gs_5gc\",instance=\"cadvisor:8080\"}) by (instance)) / sum(machine_memory_bytes{instance=\"cadvisor:8080\"}) by (instance)) * 100": 0.5495067003408319,
  "sum(container_memory_usage_bytes{name=\"open5gs_5gc\",instance=\"cadvisor:8080\"}) by (instance) - sum(container_memory_cache{name=\"open5gs_5gc\",instance=\"cadvisor:8080\"}) by (instance)": 368689152.0,
  "sum(irate(container_network_transmit_bytes_total{name=\"open5gs_5gc\",instance=\"cadvisor:8080\",interface=\"eth0\"}[5m]))by (instance)": 165.87112171837708,
  "sum(irate(container_network_transmit_bytes_total{name=\"open5gs_5gc\",instance=\"cadvisor:8080\",interface=\"eth1\"}[5m]))by (instance)": 0.0,
  "sum(irate(container_network_receive_bytes_total{name=\"open5gs_5gc\",instance=\"cadvisor:8080\",interface=\"eth0\"}[5m]))by (instance)": 1730613.3651551313,
  "sum(irate(container_network_receive_bytes_total{name=\"open5gs_5gc\",instance=\"cadvisor:8080\",interface=\"eth1\"}[5m]))by (instance)": 0.0,
  "sum  (irate(container_cpu_user_seconds_total{name=\"open5gs_5gc\",instance=\"cadvisor:8080\"}[5m]) * 100)": 2.502207637231444,
  "sum  (container_memory_usage_bytes{name=\"open5gs_5gc\",instance=\"cadvisor:8080\"} - container_memory_cache{name=\"open5gs_5gc\",instance=\"cadvisor:8080\"})": 368689152.0,
  "sum  (irate(container_network_transmit_bytes_total{name=\"open5gs_5gc\",instance=\"cadvisor:8080\",interface=\"eth0\"}[5m]))": 165.87112171837708,
  "sum  (irate(container_network_transmit_bytes_total{name=\"open5gs_5gc\",instance=\"cadvisor:8080\",interface=\"eth1\"}[5m]))": 0.0,
  "sum  (irate(container_network_receive_bytes_total{name=\"open5gs_5gc\",instance=\"cadvisor:8080\",interface=\"eth0\"}[5m]))": 1730613.3651551313,
  "sum  (irate(container_network_receive_bytes_total{name=\"open5gs_5gc\",instance=\"cadvisor:8080\",interface=\"eth1\"}[5m]))": 0.0,
  "sum(irate(container_cpu_user_seconds_total{name=\"hbbs\",instance=\"cadvisor:8080\"}[5m]) * 100)by (instance) / sum(machine_cpu_cores{instance=\"cadvisor:8080\"}) by (instance)": 0.0,
  "((sum(container_memory_usage_bytes{name=\"hbbs\",instance=\"cadvisor:8080\"}) by (instance) - sum(container_memory_cache{name=\"hbbs\",instance=\"cadvisor:8080\"}) by (instance)) / sum(machine_memory_bytes{instance=\"cadvisor:8080\"}) by (instance)) * 100": 0.0,
  "sum(container_memory_usage_bytes{name=\"hbbs\",instance=\"cadvisor:8080\"}) by (instance) - sum(container_memory_cache{name=\"hbbs\",instance=\"cadvisor:8080\"}) by (instance)": 0.0,
  "sum(irate(container_network_transmit_bytes_total{name=\"hbbs\",instance=\"cadvisor:8080\",interface=\"eth0\"}[5m]))by (instance)": 0.0,
  "sum(irate(container_network_transmit_bytes_total{name=\"hbbs\",instance=\"cadvisor:8080\",interface=\"eth1\"}[5m]))by (instance)": 0.0,
  "sum(irate(container_network_receive_bytes_total{name=\"hbbs\",instance=\"cadvisor:8080\",interface=\"eth0\"}[5m]))by (instance)": 0.0,
  "sum(irate(container_network_receive_bytes_total{name=\"hbbs\",instance=\"cadvisor:8080\",interface=\"eth1\"}[5m]))by (instance)": 0.0,
  "sum  (irate(container_cpu_user_seconds_total{name=\"hbbs\",instance=\"cadvisor:8080\"}[5m]) * 100)": 0.0,
  "sum  (container_memory_usage_bytes{name=\"hbbs\",instance=\"cadvisor:8080\"} - container_memory_cache{name=\"hbbs\",instance=\"cadvisor:8080\"})": 0.0,
  "sum  (irate(container_network_transmit_bytes_total{name=\"hbbs\",instance=\"cadvisor:8080\",interface=\"eth0\"}[5m]))": 0.0,
  "sum  (irate(container_network_transmit_bytes_total{name=\"hbbs\",instance=\"cadvisor:8080\",interface=\"eth1\"}[5m]))": 0.0,
  "sum  (irate(container_network_receive_bytes_total{name=\"hbbs\",instance=\"cadvisor:8080\",interface=\"eth0\"}[5m]))": 0.0,
  "sum  (irate(container_network_receive_bytes_total{name=\"hbbs\",instance=\"cadvisor:8080\",interface=\"eth1\"}[5m]))": 0.0,
  "sum(irate(container_cpu_user_seconds_total{name=\"srsdu1\",instance=\"cadvisor:8080\"}[5m]) * 100)by (instance) / sum(machine_cpu_cores{instance=\"cadvisor:8080\"}) by (instance)": 3.913494913225645,
  "((sum(container_memory_usage_bytes{name=\"srsdu1\",instance=\"cadvisor:8080\"}) by (instance) - sum(container_memory_cache{name=\"srsdu1\",instance=\"cadvisor:8080\"}) by (instance)) / sum(machine_memory_bytes{instance=\"cadvisor:8080\"}) by (instance)) * 100": 3.719340850803791,
  "sum(container_memory_usage_bytes{name=\"srsdu1\",instance=\"cadvisor:8080\"}) by (instance) - sum(container_memory_cache{name=\"srsdu1\",instance=\"cadvisor:8080\"}) by (instance)": 2495475712.0,
  "sum(irate(container_network_transmit_bytes_total{name=\"srsdu1\",instance=\"cadvisor:8080\",interface=\"eth0\"}[5m]))by (instance)": 163244652.90245363,
  "sum(irate(container_network_transmit_bytes_total{name=\"srsdu1\",instance=\"cadvisor:8080\",interface=\"eth1\"}[5m]))by (instance)": 15937.163375224416,
  "sum(irate(container_network_receive_bytes_total{name=\"srsdu1\",instance=\"cadvisor:8080\",interface=\"eth0\"}[5m]))by (instance)": 163122878.51585877,
  "sum(irate(container_network_receive_bytes_total{name=\"srsdu1\",instance=\"cadvisor:8080\",interface=\"eth1\"}[5m]))by (instance)": 0.0,
  "sum  (irate(container_cpu_user_seconds_total{name=\"srsdu1\",instance=\"cadvisor:8080\"}[5m]) * 100)": 109.57785757031806,
  "sum  (container_memory_usage_bytes{name=\"srsdu1\",instance=\"cadvisor:8080\"} - container_memory_cache{name=\"srsdu1\",instance=\"cadvisor:8080\"})": 2495475712.0,
  "sum  (irate(container_network_transmit_bytes_total{name=\"srsdu1\",instance=\"cadvisor:8080\",interface=\"eth0\"}[5m]))": 163244652.90245363,
  "sum  (irate(container_network_transmit_bytes_total{name=\"srsdu1\",instance=\"cadvisor:8080\",interface=\"eth1\"}[5m]))": 15937.163375224416,
  "sum  (irate(container_network_receive_bytes_total{name=\"srsdu1\",instance=\"cadvisor:8080\",interface=\"eth0\"}[5m]))": 163122878.51585877,
  "sum  (irate(container_network_receive_bytes_total{name=\"srsdu1\",instance=\"cadvisor:8080\",interface=\"eth1\"}[5m]))": 0.0,
  "sum(irate(container_cpu_user_seconds_total{name=\"srsdu2\",instance=\"cadvisor:8080\"}[5m]) * 100)by (instance) / sum(machine_cpu_cores{instance=\"cadvisor:8080\"}) by (instance)": 3.8235153827807937,
  "((sum(container_memory_usage_bytes{name=\"srsdu2\",instance=\"cadvisor:8080\"}) by (instance) - sum(container_memory_cache{name=\"srsdu2\",instance=\"cadvisor:8080\"}) by (instance)) / sum(machine_memory_bytes{instance=\"cadvisor:8080\"}) by (instance)) * 100": 3.718620482512449,
  "sum(container_memory_usage_bytes{name=\"srsdu2\",instance=\"cadvisor:8080\"}) by (instance) - sum(container_memory_cache{name=\"srsdu2\",instance=\"cadvisor:8080\"}) by (instance)": 2494992384.0,
  "sum(irate(container_network_transmit_bytes_total{name=\"srsdu2\",instance=\"cadvisor:8080\",interface=\"eth0\"}[5m]))by (instance)": 168735478.01892042,
  "sum(irate(container_network_transmit_bytes_total{name=\"srsdu2\",instance=\"cadvisor:8080\",interface=\"eth1\"}[5m]))by (instance)": 14791.318864774625,
  "sum(irate(container_network_receive_bytes_total{name=\"srsdu2\",instance=\"cadvisor:8080\",interface=\"eth0\"}[5m]))by (instance)": 168249677.79632723,
  "sum(irate(container_network_receive_bytes_total{name=\"srsdu2\",instance=\"cadvisor:8080\",interface=\"eth1\"}[5m]))by (instance)": 0.0,
  "sum  (irate(container_cpu_user_seconds_total{name=\"srsdu2\",instance=\"cadvisor:8080\"}[5m]) * 100)": 107.05843071786222,
  "sum  (container_memory_usage_bytes{name=\"srsdu2\",instance=\"cadvisor:8080\"} - container_memory_cache{name=\"srsdu2\",instance=\"cadvisor:8080\"})": 2494992384.0,
  "sum  (irate(container_network_transmit_bytes_total{name=\"srsdu2\",instance=\"cadvisor:8080\",interface=\"eth0\"}[5m]))": 168735478.01892042,
  "sum  (irate(container_network_transmit_bytes_total{name=\"srsdu2\",instance=\"cadvisor:8080\",interface=\"eth1\"}[5m]))": 14791.318864774625,
  "sum  (irate(container_network_receive_bytes_total{name=\"srsdu2\",instance=\"cadvisor:8080\",interface=\"eth0\"}[5m]))": 168249677.79632723,
  "sum  (irate(container_network_receive_bytes_total{name=\"srsdu2\",instance=\"cadvisor:8080\",interface=\"eth1\"}[5m]))": 0.0,
  "sum(irate(container_cpu_user_seconds_total{name=\"srscu2\",instance=\"cadvisor:8080\"}[5m]) * 100)by (instance) / sum(machine_cpu_cores{instance=\"cadvisor:8080\"}) by (instance)": 0.3030367425281061,
  "((sum(container_memory_usage_bytes{name=\"srscu2\",instance=\"cadvisor:8080\"}) by (instance) - sum(container_memory_cache{name=\"srscu2\",instance=\"cadvisor:8080\"}) by (instance)) / sum(machine_memory_bytes{instance=\"cadvisor:8080\"}) by (instance)) * 100": 3.424539284796383,
  "sum(container_memory_usage_bytes{name=\"srscu2\",instance=\"cadvisor:8080\"}) by (instance) - sum(container_memory_cache{name=\"srscu2\",instance=\"cadvisor:8080\"}) by (instance)": 2297679872.0,
  "sum(irate(container_network_transmit_bytes_total{name=\"srscu2\",instance=\"cadvisor:8080\",interface=\"eth0\"}[5m]))by (instance)": 864751.1196417147,
  "sum(irate(container_network_transmit_bytes_total{name=\"srscu2\",instance=\"cadvisor:8080\",interface=\"eth1\"}[5m]))by (instance)": 1460.6525911708254,
  "sum(irate(container_network_receive_bytes_total{name=\"srscu2\",instance=\"cadvisor:8080\",interface=\"eth0\"}[5m]))by (instance)": 864060.1407549585,
  "sum(irate(container_network_receive_bytes_total{name=\"srscu2\",instance=\"cadvisor:8080\",interface=\"eth1\"}[5m]))by (instance)": 0.0,
  "sum  (irate(container_cpu_user_seconds_total{name=\"srscu2\",instance=\"cadvisor:8080\"}[5m]) * 100)": 8.48502879078697,
  "sum  (container_memory_usage_bytes{name=\"srscu2\",instance=\"cadvisor:8080\"} - container_memory_cache{name=\"srscu2\",instance=\"cadvisor:8080\"})": 2297679872.0,
  "sum  (irate(container_network_transmit_bytes_total{name=\"srscu2\",instance=\"cadvisor:8080\",interface=\"eth0\"}[5m]))": 864751.1196417147,
  "sum  (irate(container_network_transmit_bytes_total{name=\"srscu2\",instance=\"cadvisor:8080\",interface=\"eth1\"}[5m]))": 1460.6525911708254,
  "sum  (irate(container_network_receive_bytes_total{name=\"srscu2\",instance=\"cadvisor:8080\",interface=\"eth0\"}[5m]))": 864060.1407549585,
  "sum  (irate(container_network_receive_bytes_total{name=\"srscu2\",instance=\"cadvisor:8080\",interface=\"eth1\"}[5m]))": 0.0,
  "sum(irate(container_cpu_user_seconds_total{name=\"srscu1\",instance=\"cadvisor:8080\"}[5m]) * 100)by (instance) / sum(machine_cpu_cores{instance=\"cadvisor:8080\"}) by (instance)": 0.3183428062436375,
  "((sum(container_memory_usage_bytes{name=\"srscu1\",instance=\"cadvisor:8080\"}) by (instance) - sum(container_memory_cache{name=\"srscu1\",instance=\"cadvisor:8080\"}) by (instance)) / sum(machine_memory_bytes{instance=\"cadvisor:8080\"}) by (instance)) * 100": 3.3680086883741716,
  "sum(container_memory_usage_bytes{name=\"srscu1\",instance=\"cadvisor:8080\"}) by (instance) - sum(container_memory_cache{name=\"srscu1\",instance=\"cadvisor:8080\"}) by (instance)": 2259750912.0,
  "sum(irate(container_network_transmit_bytes_total{name=\"srscu1\",instance=\"cadvisor:8080\",interface=\"eth0\"}[5m]))by (instance)": 288919.23990498815,
  "sum(irate(container_network_transmit_bytes_total{name=\"srscu1\",instance=\"cadvisor:8080\",interface=\"eth1\"}[5m]))by (instance)": 1368.7648456057007,
  "sum(irate(container_network_receive_bytes_total{name=\"srscu1\",instance=\"cadvisor:8080\",interface=\"eth0\"}[5m]))by (instance)": 288010.6888361045,
  "sum(irate(container_network_receive_bytes_total{name=\"srscu1\",instance=\"cadvisor:8080\",interface=\"eth1\"}[5m]))by (instance)": 0.0,
  "sum  (irate(container_cpu_user_seconds_total{name=\"srscu1\",instance=\"cadvisor:8080\"}[5m]) * 100)": 8.91359857482185,
  "sum  (container_memory_usage_bytes{name=\"srscu1\",instance=\"cadvisor:8080\"} - container_memory_cache{name=\"srscu1\",instance=\"cadvisor:8080\"})": 2259750912.0,
  "sum  (irate(container_network_transmit_bytes_total{name=\"srscu1\",instance=\"cadvisor:8080\",interface=\"eth0\"}[5m]))": 288919.23990498815,
  "sum  (irate(container_network_transmit_bytes_total{name=\"srscu1\",instance=\"cadvisor:8080\",interface=\"eth1\"}[5m]))": 1368.7648456057007,
  "sum  (irate(container_network_receive_bytes_total{name=\"srscu1\",instance=\"cadvisor:8080\",interface=\"eth0\"}[5m]))": 288010.6888361045,
  "sum  (irate(container_network_receive_bytes_total{name=\"srscu1\",instance=\"cadvisor:8080\",interface=\"eth1\"}[5m]))": 0.0,
  "PCI-1_RNTI-4601_bsr": 0.0,
  "PCI-1_RNTI-4601_ul_brate": 3363584.0,
  "PCI-2_RNTI-4601_bsr": 2014.0,
  "PCI-2_RNTI-4601_ul_brate": 3578832.0,
  "PCI-3_RNTI-4601_bsr": 3909.0,
  "PCI-3_RNTI-4601_ul_brate": 2889936.0,
  "PCI-4_RNTI-4601_bsr": 2806.0,
  "PCI-4_RNTI-4601_ul_brate": 2970928.0,
  "PCI-5_RNTI-4601_bsr": 2014.0,
  "PCI-5_RNTI-4601_ul_brate": 3123552.0,
  "PCI-6_RNTI-4601_bsr": 0.0,
  "PCI-6_RNTI-4601_ul_brate": 3443712.0,
  "_timestamp": "2026-05-12 04:08:18.662",
  "_phase": "NORMAL"
}